fitdown/__init__.py
fitdown/parse.py
fitdown-0.0.1.dist-info/LICENSE
fitdown-0.0.1.dist-info/METADATA
fitdown-0.0.1.dist-info/WHEEL
fitdown-0.0.1.dist-info/top_level.txt
fitdown-0.0.1.dist-info/RECORD
