Metadata-Version: 2.1
Name: fitdown
Version: 0.0.1
Summary: Parser for weightlifting logs
Author-email: Luca Grippa <luca@pypi.lucagrippa.io>
Project-URL: Homepage, https://github.com/lucagrippa/fitdown-py
Project-URL: Issues, https://github.com/lucagrippa/fitdown-py/issues
Classifier: Programming Language :: Python :: 3
Classifier: License :: OSI Approved :: MIT License
Classifier: Operating System :: OS Independent
Classifier: Topic :: Text Processing :: Markup
Requires-Python: >=3.8
License-File: LICENSE
